aspanner/__init__.py
aspanner/client.py
aspanner/pool.py
aspanner/resultset.py
aspanner/session.py
aspanner/transaction.py
aspanner-0.6.1.dist-info/LICENSE
aspanner-0.6.1.dist-info/METADATA
aspanner-0.6.1.dist-info/WHEEL
aspanner-0.6.1.dist-info/top_level.txt
aspanner-0.6.1.dist-info/RECORD
