Metadata-Version: 2.1
Name: aspanner
Version: 0.6.1
Summary: Asyncio Client for Google-Spanner, wrapped google-cloud-spanner.
Home-page: http://github.com/lovinjoy/aspanner
Author: LovinJoy
Author-email: technical-committee@lovinjoy.com
License: MIT License
Keywords: spanner,database,asyncio
Requires-Python: >=3.8
License-File: LICENSE
Requires-Dist: google-cloud-spanner (>=3.14.0)
